ml_study-0.0.1.dist-info/METADATA
ml_study-0.0.1.dist-info/RECORD
ml_study-0.0.1.dist-info/WHEEL
ml_study-0.0.1.dist-info/entry_points.txt
ml_study-0.0.1.dist-info/top_level.txt
src/__init__.py
src/cli.py
src/data/__init__.py
src/data/download.py
src/data/preprocess.py
src/models/__init__.py
src/models/random_forest.py
src/models/train_model.py
src/tests/__init__.py
src/tests/test_data.py
src/visualization/__init__.py
src/visualization/exploratory.py
